sakkara/__init__.py
sakkara/model/__init__.py
sakkara/model/base.py
sakkara/model/composable/__init__.py
sakkara/model/composable/base.py
sakkara/model/composable/group.py
sakkara/model/composable/hierarchical/__init__.py
sakkara/model/composable/hierarchical/base.py
sakkara/model/composable/hierarchical/distribution.py
sakkara/model/composable/hierarchical/likelihood.py
sakkara/model/composable/hierarchical/reshaper.py
sakkara/model/deterministic.py
sakkara/model/fixed/__init__.py
sakkara/model/fixed/base.py
sakkara/model/fixed/data.py
sakkara/model/function/__init__.py
sakkara/model/function/base.py
sakkara/model/function/wrapper.py
sakkara/model/math_op.py
sakkara/model/minibatch.py
sakkara/model/utils.py
sakkara/model/wrapper.py
sakkara/relation/__init__.py
sakkara/relation/group.py
sakkara/relation/groupset.py
sakkara/relation/representation.py
sakkara-0.6.2.dist-info/LICENSE
sakkara-0.6.2.dist-info/METADATA
sakkara-0.6.2.dist-info/WHEEL
sakkara-0.6.2.dist-info/RECORD
